COPYING
MANIFEST.in
README.rst
setup.py
tests.py
tomsbestfriend.py
tox.ini
toml-test/.gitignore
toml-test/COPYING
toml-test/README.md
toml-test/json.go
toml-test/main.go
toml-test/results.go
toml-test/tests/invalid/array-mixed-types-arrays-and-ints.toml
toml-test/tests/invalid/array-mixed-types-ints-and-floats.toml
toml-test/tests/invalid/array-mixed-types-strings-and-ints.toml
toml-test/tests/invalid/datetime-malformed-no-leads.toml
toml-test/tests/invalid/datetime-malformed-no-secs.toml
toml-test/tests/invalid/datetime-malformed-no-t.toml
toml-test/tests/invalid/datetime-malformed-no-z.toml
toml-test/tests/invalid/datetime-malformed-with-milli.toml
toml-test/tests/invalid/duplicate-key-keygroup.toml
toml-test/tests/invalid/duplicate-keygroups.toml
toml-test/tests/invalid/duplicate-keys.toml
toml-test/tests/invalid/empty-implicit-keygroup.toml
toml-test/tests/invalid/empty-keygroup.toml
toml-test/tests/invalid/float-no-leading-zero.toml
toml-test/tests/invalid/float-no-trailing-digits.toml
toml-test/tests/invalid/key-two-equals.toml
toml-test/tests/invalid/keygroup-nested-brackets-close.toml
toml-test/tests/invalid/keygroup-nested-brackets-open.toml
toml-test/tests/invalid/string-bad-byte-escape.toml
toml-test/tests/invalid/string-bad-escape.toml
toml-test/tests/invalid/string-byte-escapes.toml
toml-test/tests/invalid/string-no-close.toml
toml-test/tests/invalid/text-after-array-entries.toml
toml-test/tests/invalid/text-after-integer.toml
toml-test/tests/invalid/text-after-keygroup.toml
toml-test/tests/invalid/text-after-string.toml
toml-test/tests/invalid/text-before-array-separator.toml
toml-test/tests/invalid/text-in-array.toml
toml-test/tests/valid/array-empty.json
toml-test/tests/valid/array-empty.toml
toml-test/tests/valid/arrays-hetergeneous.json
toml-test/tests/valid/arrays-hetergeneous.toml
toml-test/tests/valid/arrays-nested.json
toml-test/tests/valid/arrays-nested.toml
toml-test/tests/valid/arrays.json
toml-test/tests/valid/arrays.toml
tomsbestfriend.egg-info/PKG-INFO
tomsbestfriend.egg-info/SOURCES.txt
tomsbestfriend.egg-info/dependency_links.txt
tomsbestfriend.egg-info/requires.txt
tomsbestfriend.egg-info/top_level.txt